telegant/__init__.py
telegant/method.py
telegant/telegant.py
telegant/handlers/CallbackQueryHandler.py
telegant/handlers/CommandHandler.py
telegant/handlers/EventHandler.py
telegant/handlers/TextHandler.py
telegant/handlers/UpdateHandler.py
telegant/handlers/__init__.py
Telegant-0.2.6.dist-info/LICENSE
Telegant-0.2.6.dist-info/METADATA
Telegant-0.2.6.dist-info/WHEEL
Telegant-0.2.6.dist-info/top_level.txt
Telegant-0.2.6.dist-info/RECORD
