Metadata-Version: 2.1
Name: Telegant
Version: 0.2.6
Summary: An Elegant Modern Bot Framework for Python
Home-page: https://github.com/kotov584/Telegant
Author: Kotov584
License: MIT
Keywords: python,telegram,bot,api,async,asynchronous,elegant,modern
Requires-Python: >=3.6
License-File: LICENSE
Requires-Dist: aiohttp
